mudyla/__init__.py
mudyla/__main__.py
mudyla/axis_wildcards.py
mudyla/cli.py
mudyla/cli_args.py
mudyla/cli_builder.py
mudyla/runtime.py
mudyla/runtime.sh
mudyla/ast/__init__.py
mudyla/ast/expansions.py
mudyla/ast/models.py
mudyla/ast/types.py
mudyla/dag/__init__.py
mudyla/dag/builder.py
mudyla/dag/compiler.py
mudyla/dag/context.py
mudyla/dag/graph.py
mudyla/dag/validator.py
mudyla/executor/__init__.py
mudyla/executor/bash_runtime.py
mudyla/executor/engine.py
mudyla/executor/language_runtime.py
mudyla/executor/python_runtime.py
mudyla/executor/retainer_executor.py
mudyla/executor/runtime_registry.py
mudyla/executor/task_table.py
mudyla/parser/__init__.py
mudyla/parser/combinators.py
mudyla/parser/dependency_parser.py
mudyla/parser/expansion_parser.py
mudyla/parser/markdown_parser.py
mudyla/parser/return_parser.py
mudyla/utils/__init__.py
mudyla/utils/colors.py
mudyla/utils/context_ids.py
mudyla/utils/output.py
mudyla/utils/project_root.py
mudyla-0.4.0.dist-info/METADATA
mudyla-0.4.0.dist-info/WHEEL
mudyla-0.4.0.dist-info/entry_points.txt
mudyla-0.4.0.dist-info/licenses/LICENSE
mudyla-0.4.0.dist-info/RECORD
