Metadata-Version: 2.4
Name: mudyla
Version: 0.4.0
Summary: Multimodal Dynamic Launcher - Shell script orchestrator
Author-email: Pavel <pavel@example.com>
License: MIT
License-File: LICENSE
Keywords: automation,build,nix,orchestrator,shell
Classifier: Development Status :: 3 - Alpha
Classifier: Intended Audience :: Developers
Classifier: License :: OSI Approved :: MIT License
Classifier: Programming Language :: Python :: 3
Classifier: Programming Language :: Python :: 3.12
Requires-Python: >=3.12
Requires-Dist: mistune>=3.0.0
Requires-Dist: pyparsing>=3.0.0
Requires-Dist: rich>=13.0.0
Provides-Extra: dev
Requires-Dist: mypy>=1.0.0; extra == 'dev'
Requires-Dist: pytest-html>=4.0.0; extra == 'dev'
Requires-Dist: pytest-xdist>=3.0.0; extra == 'dev'
Requires-Dist: pytest>=7.0.0; extra == 'dev'
